myconfig/__init__.py
myconfig/const.py
myconfig/myconfig.py
myconfig-0.2.9.dist-info/LICENSE
myconfig-0.2.9.dist-info/METADATA
myconfig-0.2.9.dist-info/WHEEL
myconfig-0.2.9.dist-info/entry_points.txt
myconfig-0.2.9.dist-info/top_level.txt
myconfig-0.2.9.dist-info/RECORD
