Metadata-Version: 2.1
Name: myconfig
Version: 0.2.9
Summary: Python Projects Configuration Manager
Home-page: https://github.com/azureswastika/myconfig
Author: Deni
License: MIT license
Download-URL: https://github.com/azureswastika/myconfig/archive/0.2.9.tar.gz
Keywords: myconfig,config,project config
Platform: UNKNOWN
Classifier: Development Status :: 3 - Alpha
Classifier: License :: OSI Approved :: MIT License
Classifier: Programming Language :: Python
Classifier: Programming Language :: Python :: 3
Classifier: Programming Language :: Python :: 3.6
Classifier: Programming Language :: Python :: 3.7
Classifier: Programming Language :: Python :: 3.8
Classifier: Programming Language :: Python :: 3.9
Classifier: Programming Language :: Python :: 3 :: Only
Requires-Python: >=3.6
Requires-Dist: PyYAML (>=5.4.1)
Requires-Dist: toml (>=0.10.2)
